safe_eth/__init__.py
safe_eth/py.typed
safe_eth/eth/__init__.py
safe_eth/eth/constants.py
safe_eth/eth/ethereum_client.py
safe_eth/eth/ethereum_network.py
safe_eth/eth/exceptions.py
safe_eth/eth/multicall.py
safe_eth/eth/typing.py
safe_eth/eth/utils.py
safe_eth/eth/account_abstraction/__init__.py
safe_eth/eth/account_abstraction/bundler_client.py
safe_eth/eth/account_abstraction/constants.py
safe_eth/eth/account_abstraction/exceptions.py
safe_eth/eth/account_abstraction/user_operation.py
safe_eth/eth/account_abstraction/user_operation_receipt.py
safe_eth/eth/clients/__init__.py
safe_eth/eth/clients/blockscout_client.py
safe_eth/eth/clients/contract_metadata.py
safe_eth/eth/clients/ens_client.py
safe_eth/eth/clients/etherscan_client_v2.py
safe_eth/eth/clients/sourcify_client.py
safe_eth/eth/clients/cowswap/__init__.py
safe_eth/eth/clients/cowswap/cow_swap_api.py
safe_eth/eth/clients/cowswap/order.py
safe_eth/eth/clients/cowswap/tests/__init__.py
safe_eth/eth/clients/cowswap/tests/test_cow_swap_api.py
safe_eth/eth/contracts/__init__.py
safe_eth/eth/contracts/contract_base.py
safe_eth/eth/contracts/abis/CPKFactory.json
safe_eth/eth/contracts/abis/CompatibilityFallbackHandler_V1_3_0.json
safe_eth/eth/contracts/abis/CompatibilityFallbackHandler_V1_4_1.json
safe_eth/eth/contracts/abis/CompatibilityFallbackHandler_V1_5_0.json
safe_eth/eth/contracts/abis/DelegateConstructorProxy.json
safe_eth/eth/contracts/abis/ERC1155.json
safe_eth/eth/contracts/abis/ERC20.json
safe_eth/eth/contracts/abis/ERC20TestToken.json
safe_eth/eth/contracts/abis/ERC721.json
safe_eth/eth/contracts/abis/ExtensibleFallbackHandler_V1_5_0.json
safe_eth/eth/contracts/abis/GnosisSafe_V0_0_1.json
safe_eth/eth/contracts/abis/GnosisSafe_V1_0_0.json
safe_eth/eth/contracts/abis/GnosisSafe_V1_1_1.json
safe_eth/eth/contracts/abis/GnosisSafe_V1_3_0.json
safe_eth/eth/contracts/abis/MultiSendCallOnly_V1_4_1.json
safe_eth/eth/contracts/abis/MultiSendCallOnly_V1_5_0.json
safe_eth_py-7.18.0.dist-info/METADATA
safe_eth_py-7.18.0.dist-info/WHEEL
safe_eth_py-7.18.0.dist-info/licenses/LICENSE
safe_eth_py-7.18.0.dist-info/RECORD
